{
    "p_values": {
        "1": 2.8257490467800966e-110,
        "2": 0.0,
        "3": 0.0,
        "4": 0.005550980315606796,
        "5": 0.8240695879548099,
        "6": 1.42129313879817e-05,
        "7": 1.3472406079700675e-87,
        "8": 1.4445258980473514e-09,
        "9": 3.216180751368936e-67,
        "10": 0.2499518240740445,
        "12": 1.9870102103261087e-121,
        "14": [
            0.16334822611899405,
            0.5708314605335711,
            0.12468524616167655,
            0.6212271284510297,
            0.7526650351046936,
            0.8324644957333858,
            0.7675784604257123,
            0.33892179135820444
        ],
        "15": [
            0.35359763279966683,
            0.338728407239979,
            0.2887854975121197,
            0.22047164360629323,
            0.17554744858249927,
            0.1360171528463192,
            0.12111386765685236,
            0.16754627748861728,
            0.47328946538009,
            0.7199178531944465,
            0.6788452994243183,
            0.4226780741706355,
            0.2059032107320684
        ]
    },
    "pass_status": {
        "1": 0,
        "2": 0,
        "3": 0,
        "4": 0,
        "5": 1,
        "6": 0,
        "7": 0,
        "8": 0,
        "9": 0,
        "10": 1,
        "11": 1,
        "12": 0,
        "13": 1,
        "14": 1,
        "15": 1
    },
    "test_names": {
        "1": "Frequency Test",
        "2": "Block Frequency Test",
        "3": "Run Test",
        "4": "Longest Run of Ones Test",
        "5": "Binary Matrix Rank Test",
        "6": "Spectral Test",
        "7": "Non-overlapping Template Test",
        "8": "Overlapping Template Test",
        "9": "Universal Statistical Test",
        "10": "Linear Complexity Test",
        "11": "Serial Test",
        "12": "Approximate Entropy Test",
        "13": "Cumulative Sums Test",
        "14": "Random Excursions Test",
        "15": "Random Excursions Variant Test"
    },
    "pass_rate": 40.0
}