{
    "p_values": {
        "1": 1.4880525192364771e-74,
        "2": 0.0,
        "3": 0.0,
        "4": 0.001598348785504904,
        "5": 0.095558106767859,
        "6": 4.779019377679655e-09,
        "7": 3.714060623603174e-84,
        "8": 1.0814972470831018e-07,
        "9": 6.297492749021493e-50,
        "10": 0.6278234918267704,
        "12": 4.034400769127195e-87,
        "14": [
            0.8576543411668496,
            0.8371203880763571,
            0.7514663600710249,
            0.724969290951353,
            0.9266637542891779,
            0.8697278336049776,
            0.587182413206432,
            0.3575072782451603
        ],
        "15": [
            0.7351142739413705,
            0.5284883562390079,
            0.45836017119551864,
            0.6740473527050261,
            0.756565744690396,
            0.5384723809869921,
            0.4355010313614208,
            0.4205962375999266,
            0.7272823220714765,
            0.3523808651090834,
            0.7371890955213669,
            0.567414948534378,
            0.4038235272880347,
            0.641938220405063,
            0.8608832691379124,
            1.0,
            0.9044355828278577,
            0.8878928769706363
        ]
    },
    "pass_status": {
        "1": 0,
        "2": 0,
        "3": 0,
        "4": 0,
        "5": 1,
        "6": 0,
        "7": 0,
        "8": 0,
        "9": 0,
        "10": 1,
        "11": 1,
        "12": 0,
        "13": 1,
        "14": 1,
        "15": 1
    },
    "test_names": {
        "1": "Frequency Test",
        "2": "Block Frequency Test",
        "3": "Run Test",
        "4": "Longest Run of Ones Test",
        "5": "Binary Matrix Rank Test",
        "6": "Spectral Test",
        "7": "Non-overlapping Template Test",
        "8": "Overlapping Template Test",
        "9": "Universal Statistical Test",
        "10": "Linear Complexity Test",
        "11": "Serial Test",
        "12": "Approximate Entropy Test",
        "13": "Cumulative Sums Test",
        "14": "Random Excursions Test",
        "15": "Random Excursions Variant Test"
    },
    "pass_rate": 40.0
}