{
    "p_values": {
        "1": 0.00011908605341066129,
        "2": 0.0,
        "3": 2.9828059530555917e-21,
        "4": 0.11877589837019001,
        "5": 0.8328875725444838,
        "6": 8.713273969859347e-07,
        "7": 3.0694707947175164e-31,
        "8": 2.8484421730236984e-10,
        "9": 3.9488070803687256e-38,
        "10": 0.4343393246920121,
        "12": 6.28990773770171e-51,
        "14": [
            0.5431055508190584,
            0.38600562777146874,
            0.41262898294249223,
            0.6441139579291723,
            0.9776095629823318,
            0.9644884640809234,
            0.638938797900196,
            0.31678308620432866
        ],
        "15": [
            0.5951195717299176,
            0.7146911306735741,
            0.6603535533003132,
            0.854836453113157,
            0.9910346276463928,
            0.7890343476731525,
            0.8446239619988356,
            0.7703347136423385,
            0.7874064906662692,
            0.6131024469227179,
            0.7554968749288828,
            0.8682897609105342,
            0.5408179042426179,
            0.33386750568353574,
            0.36032022061670577,
            0.4106482693074591,
            0.49719941458086114,
            0.4182784602423938
        ]
    },
    "pass_status": {
        "1": 0,
        "2": 0,
        "3": 0,
        "4": 1,
        "5": 1,
        "6": 0,
        "7": 0,
        "8": 0,
        "9": 0,
        "10": 1,
        "11": 1,
        "12": 0,
        "13": 1,
        "14": 1,
        "15": 1
    },
    "test_names": {
        "1": "Frequency Test",
        "2": "Block Frequency Test",
        "3": "Run Test",
        "4": "Longest Run of Ones Test",
        "5": "Binary Matrix Rank Test",
        "6": "Spectral Test",
        "7": "Non-overlapping Template Test",
        "8": "Overlapping Template Test",
        "9": "Universal Statistical Test",
        "10": "Linear Complexity Test",
        "11": "Serial Test",
        "12": "Approximate Entropy Test",
        "13": "Cumulative Sums Test",
        "14": "Random Excursions Test",
        "15": "Random Excursions Variant Test"
    },
    "pass_rate": 46.666666666666664
}