{
    "p_values": {
        "1": 1.6342815981172535e-40,
        "2": 0.0,
        "3": 0.0,
        "4": 0.009734153437181854,
        "5": 0.7713781150321267,
        "6": 1.9800143636442086e-05,
        "7": 1.1527636050657083e-58,
        "8": 5.819008171878823e-13,
        "9": 4.382870118969048e-52,
        "10": 0.2058719708023766,
        "12": 2.7654625144173183e-69,
        "14": [
            0.22335592690151532,
            0.5838044685853617,
            0.3763355623525705,
            0.5940111162159522,
            0.5161317713138242,
            0.6445935976402069,
            0.2854780818183142,
            0.8492046671930651
        ],
        "15": [
            0.5433809107860981,
            0.1731945874792824,
            0.0674307154607185,
            0.18284979043287142,
            0.48184440462705436,
            0.8615073626021822,
            0.9295069631495971,
            0.9393087523212691,
            0.46825664615340634,
            0.35593807492841845,
            0.5940537303751279,
            0.5553463166714221,
            0.6718006119009301,
            0.7086655217937303,
            0.6763109285820306,
            0.8981367326247249,
            0.972837071249517,
            1.0
        ]
    },
    "pass_status": {
        "1": 0,
        "2": 0,
        "3": 0,
        "4": 0,
        "5": 1,
        "6": 0,
        "7": 0,
        "8": 0,
        "9": 0,
        "10": 1,
        "11": 1,
        "12": 0,
        "13": 1,
        "14": 1,
        "15": 1
    },
    "test_names": {
        "1": "Frequency Test",
        "2": "Block Frequency Test",
        "3": "Run Test",
        "4": "Longest Run of Ones Test",
        "5": "Binary Matrix Rank Test",
        "6": "Spectral Test",
        "7": "Non-overlapping Template Test",
        "8": "Overlapping Template Test",
        "9": "Universal Statistical Test",
        "10": "Linear Complexity Test",
        "11": "Serial Test",
        "12": "Approximate Entropy Test",
        "13": "Cumulative Sums Test",
        "14": "Random Excursions Test",
        "15": "Random Excursions Variant Test"
    },
    "pass_rate": 40.0
}