{
    "p_values": {
        "1": 0.0009531583224111877,
        "2": 0.0,
        "3": 1.0540003304660383e-25,
        "4": 0.00016300204460886105,
        "5": 0.48369320587098136,
        "6": 3.0463099638993374e-07,
        "7": 1.618692170117877e-27,
        "8": 9.648449594022726e-10,
        "9": 9.540344828805009e-64,
        "10": 0.4758809664802427,
        "12": 3.421995537020456e-58,
        "14": [
            0.14241453292390993,
            0.014976025561784864,
            0.5921702221598212,
            0.5896480255335307,
            0.9562925436327516,
            0.7278454283829466,
            0.2773849321617951,
            0.04828011116752641
        ],
        "15": [
            0.9084096534501656,
            0.9349253116421173,
            0.6930819368648844,
            0.8301344902219341,
            0.9579672518055619,
            0.9285715917804441,
            0.7772974107895215,
            1.0,
            0.7518296340458492,
            0.6926327840419602,
            0.4652088184521418,
            0.14717877343162764,
            0.08308118696647387,
            0.10229172467490198,
            0.17424668418513345,
            0.2542132236039645,
            0.29786016754980627,
            0.29161889165097277
        ]
    },
    "pass_status": {
        "1": 0,
        "2": 0,
        "3": 0,
        "4": 0,
        "5": 1,
        "6": 0,
        "7": 0,
        "8": 0,
        "9": 0,
        "10": 1,
        "11": 1,
        "12": 0,
        "13": 1,
        "14": 1,
        "15": 1
    },
    "test_names": {
        "1": "Frequency Test",
        "2": "Block Frequency Test",
        "3": "Run Test",
        "4": "Longest Run of Ones Test",
        "5": "Binary Matrix Rank Test",
        "6": "Spectral Test",
        "7": "Non-overlapping Template Test",
        "8": "Overlapping Template Test",
        "9": "Universal Statistical Test",
        "10": "Linear Complexity Test",
        "11": "Serial Test",
        "12": "Approximate Entropy Test",
        "13": "Cumulative Sums Test",
        "14": "Random Excursions Test",
        "15": "Random Excursions Variant Test"
    },
    "pass_rate": 40.0
}