{
    "p_values": {
        "1": 0.5713937805168801,
        "2": 0.0,
        "3": 1.9742826078034384e-25,
        "4": 0.00020341422989707036,
        "5": 0.34510052091437854,
        "6": 1.9800143636442086e-05,
        "7": 7.408352508433294e-19,
        "8": 2.6155236012001007e-12,
        "9": 8.882639350686056e-53,
        "10": 0.48335428817414317,
        "12": 3.592834274661377e-76,
        "14": [
            0.36076424257905665,
            0.41382078050419946,
            0.3851811898975194,
            0.5859411184149708,
            0.5185112877220155,
            0.6213999892148896,
            0.78310261742702,
            0.39934116170247674
        ],
        "15": [
            0.7938117351773128,
            0.9722548360079944,
            0.7936906587094655,
            0.578847725494346,
            0.3457178159477038,
            0.17456255799840414,
            0.15983288631769965,
            0.12613961020268977,
            0.138408493450291,
            0.5295988084250076,
            0.6783024655972324,
            0.8565839457410922,
            0.932376246800651,
            0.7532861518018312,
            0.7350192210693068,
            0.9602709702338132,
            0.9261039382952407,
            0.8531247910356067
        ]
    },
    "pass_status": {
        "1": 1,
        "2": 0,
        "3": 0,
        "4": 0,
        "5": 1,
        "6": 0,
        "7": 0,
        "8": 0,
        "9": 0,
        "10": 1,
        "11": 1,
        "12": 0,
        "13": 1,
        "14": 1,
        "15": 1
    },
    "test_names": {
        "1": "Frequency Test",
        "2": "Block Frequency Test",
        "3": "Run Test",
        "4": "Longest Run of Ones Test",
        "5": "Binary Matrix Rank Test",
        "6": "Spectral Test",
        "7": "Non-overlapping Template Test",
        "8": "Overlapping Template Test",
        "9": "Universal Statistical Test",
        "10": "Linear Complexity Test",
        "11": "Serial Test",
        "12": "Approximate Entropy Test",
        "13": "Cumulative Sums Test",
        "14": "Random Excursions Test",
        "15": "Random Excursions Variant Test"
    },
    "pass_rate": 46.666666666666664
}