{
    "p_values": {
        "1": 1.544712299636596e-22,
        "2": 0.0,
        "3": 0.0,
        "4": 0.0019219253906823234,
        "5": 0.7310731210007649,
        "6": 2.092106218805301e-06,
        "7": 2.557284848372291e-35,
        "8": 1.6958748537523928e-08,
        "9": 1.3119240834627257e-58,
        "10": 0.956673081969929,
        "12": 2.0554944082382404e-55,
        "14": [
            1.426333953909675e-07,
            0.042394043758149244,
            0.10599809955240791,
            0.0028515276502876527,
            0.6762809834794611,
            0.6399009195949905,
            0.5622258493170158,
            0.8712557845329562
        ],
        "15": [
            0.8491049281482184,
            0.9596148041121082,
            0.9133724990484696,
            0.6789336650336024,
            0.47208393087128464,
            0.4585422862551144,
            0.7924600886080352,
            0.5712996214994486,
            0.43276758066778476,
            0.84451926747294,
            0.8208472385419284,
            0.7257209852083116,
            0.4585422862551144,
            0.6948866023724735,
            0.4077626167257874,
            0.1738866597606089,
            0.20554021822261903,
            0.19905133545968368
        ]
    },
    "pass_status": {
        "1": 0,
        "2": 0,
        "3": 0,
        "4": 0,
        "5": 1,
        "6": 0,
        "7": 0,
        "8": 0,
        "9": 0,
        "10": 1,
        "11": 1,
        "12": 0,
        "13": 1,
        "14": 0,
        "15": 1
    },
    "test_names": {
        "1": "Frequency Test",
        "2": "Block Frequency Test",
        "3": "Run Test",
        "4": "Longest Run of Ones Test",
        "5": "Binary Matrix Rank Test",
        "6": "Spectral Test",
        "7": "Non-overlapping Template Test",
        "8": "Overlapping Template Test",
        "9": "Universal Statistical Test",
        "10": "Linear Complexity Test",
        "11": "Serial Test",
        "12": "Approximate Entropy Test",
        "13": "Cumulative Sums Test",
        "14": "Random Excursions Test",
        "15": "Random Excursions Variant Test"
    },
    "pass_rate": 33.33333333333333
}