{
    "p_values": {
        "1": 0.0023036992739817333,
        "2": 0.0,
        "3": 2.2248358370530464e-24,
        "4": 0.11655603273991966,
        "5": 0.7857996125939107,
        "6": 1.1003306185110444e-06,
        "7": 4.172015234430365e-26,
        "8": 7.04838942155549e-12,
        "9": 5.772309361104015e-58,
        "10": 0.9841717482724825,
        "12": 5.558927586164277e-71,
        "14": [
            0.4434374907941496,
            0.785585380413818,
            0.7545235393959738,
            0.5644041779004424,
            0.30733896664558386,
            0.28369496435181646,
            0.48728045817730636,
            0.9536010334941352
        ],
        "15": [
            0.7968606661903517,
            0.49328696853893605,
            0.2562093257853214,
            0.07460482156057316,
            0.08122441376507922,
            0.2890644138278021,
            0.4355244843142081,
            0.6936406217837583,
            0.8794869666961451,
            0.5441970982678067,
            0.5400328254464786,
            0.8124068205005608,
            0.818692253516401,
            0.7810359387483388,
            0.5990807719790572,
            0.5560464442142687,
            0.5836423249678386,
            0.5318767740381979
        ]
    },
    "pass_status": {
        "1": 0,
        "2": 0,
        "3": 0,
        "4": 1,
        "5": 1,
        "6": 0,
        "7": 0,
        "8": 0,
        "9": 0,
        "10": 1,
        "11": 1,
        "12": 0,
        "13": 1,
        "14": 1,
        "15": 1
    },
    "test_names": {
        "1": "Frequency Test",
        "2": "Block Frequency Test",
        "3": "Run Test",
        "4": "Longest Run of Ones Test",
        "5": "Binary Matrix Rank Test",
        "6": "Spectral Test",
        "7": "Non-overlapping Template Test",
        "8": "Overlapping Template Test",
        "9": "Universal Statistical Test",
        "10": "Linear Complexity Test",
        "11": "Serial Test",
        "12": "Approximate Entropy Test",
        "13": "Cumulative Sums Test",
        "14": "Random Excursions Test",
        "15": "Random Excursions Variant Test"
    },
    "pass_rate": 46.666666666666664
}