{
    "p_values": {
        "1": 0.0001543278226482538,
        "2": 0.0,
        "3": 1.149048472295111e-28,
        "4": 0.2516957321447434,
        "5": 0.17053719125026395,
        "6": 0.0004882537711704653,
        "7": 6.884882789379541e-29,
        "8": 1.4167359276440636e-05,
        "9": 3.0151992011461125e-31,
        "10": 0.3797063791575737,
        "12": 5.437991089403781e-52,
        "14": [
            0.0292148059317604,
            0.001552798734339996,
            0.005892996092848444,
            0.005285841630599276,
            0.036756096104035275,
            0.06520666338782014,
            0.395620912831471,
            0.39756048028488794
        ],
        "15": [
            0.20757844233562428,
            0.35795311514562755,
            0.7286331397011505,
            0.734998233029868,
            0.638045297142464,
            0.5853789284609615,
            0.1555803477921979,
            0.012419330651552277,
            0.0025693570439509813,
            0.050397349322509624,
            0.13847831606682062,
            0.13954931261278272,
            0.11784225710751713,
            0.050397349322509624,
            0.030288291219514474,
            0.07093556489051098,
            0.0849607916335704,
            0.08557199609321398
        ]
    },
    "pass_status": {
        "1": 0,
        "2": 0,
        "3": 0,
        "4": 1,
        "5": 1,
        "6": 0,
        "7": 0,
        "8": 0,
        "9": 0,
        "10": 1,
        "11": 1,
        "12": 0,
        "13": 1,
        "14": 0,
        "15": 0
    },
    "test_names": {
        "1": "Frequency Test",
        "2": "Block Frequency Test",
        "3": "Run Test",
        "4": "Longest Run of Ones Test",
        "5": "Binary Matrix Rank Test",
        "6": "Spectral Test",
        "7": "Non-overlapping Template Test",
        "8": "Overlapping Template Test",
        "9": "Universal Statistical Test",
        "10": "Linear Complexity Test",
        "11": "Serial Test",
        "12": "Approximate Entropy Test",
        "13": "Cumulative Sums Test",
        "14": "Random Excursions Test",
        "15": "Random Excursions Variant Test"
    },
    "pass_rate": 33.33333333333333
}