{
    "p_values": {
        "1": 9.779145666318785e-06,
        "2": 0.0,
        "3": 0.0,
        "4": 0.0006449558732671985,
        "5": 0.2817032381381333,
        "6": 0.0003968361906050325,
        "7": 2.0969018301521527e-34,
        "8": 9.002453578965143e-11,
        "9": 2.9966680146941375e-64,
        "10": 0.8881443446460447,
        "12": 1.6368064695414184e-74,
        "14": [
            0.02477972328539544,
            0.15684298274844677,
            0.8412856503488211,
            0.5327268794704098,
            0.22668054322114153,
            0.7046123799127613,
            0.4551301724430986,
            0.5497617866767616
        ],
        "15": [
            0.9092641967597266,
            0.65111186487286,
            0.4994692318013343,
            0.5535314789008745,
            0.3929068492880623,
            0.41025899135337685,
            0.5665630808084937,
            0.6218263276782892,
            0.5786672682847314,
            0.8643247819597492,
            0.657087944020319,
            0.9542966184393618,
            0.9100139898147463,
            0.8197794072107428,
            0.7967167673121572,
            0.8035124051909338,
            0.8772817868268551,
            0.8764987897614077
        ]
    },
    "pass_status": {
        "1": 0,
        "2": 0,
        "3": 0,
        "4": 0,
        "5": 1,
        "6": 0,
        "7": 0,
        "8": 0,
        "9": 0,
        "10": 1,
        "11": 1,
        "12": 0,
        "13": 1,
        "14": 1,
        "15": 1
    },
    "test_names": {
        "1": "Frequency Test",
        "2": "Block Frequency Test",
        "3": "Run Test",
        "4": "Longest Run of Ones Test",
        "5": "Binary Matrix Rank Test",
        "6": "Spectral Test",
        "7": "Non-overlapping Template Test",
        "8": "Overlapping Template Test",
        "9": "Universal Statistical Test",
        "10": "Linear Complexity Test",
        "11": "Serial Test",
        "12": "Approximate Entropy Test",
        "13": "Cumulative Sums Test",
        "14": "Random Excursions Test",
        "15": "Random Excursions Variant Test"
    },
    "pass_rate": 40.0
}