{
    "p_values": {
        "1": 1.0608584059501904e-06,
        "2": 0.0,
        "3": 0.0,
        "4": 0.006356082160071126,
        "5": 0.9912020602003451,
        "6": 8.796642475498627e-08,
        "7": 4.886752768727159e-42,
        "8": 2.04029988241621e-09,
        "9": 6.305925285575259e-66,
        "10": 0.5400372592176161,
        "12": 4.757416078403171e-75,
        "14": [
            0.06448106769007968,
            0.3756560002734163,
            0.7655305109741642,
            0.5054962725345239,
            0.6848245666519681,
            0.9388850233008948,
            0.6773280408212933,
            0.5550653502594373
        ],
        "15": [
            0.8261971492893773,
            0.9069542394024853,
            0.8407917932858895,
            0.7432363132296949,
            0.9278614893440519,
            0.784273396256489,
            0.6855597181184911,
            0.8753926116652608,
            0.5262438434591222,
            0.3652760444092834,
            0.8753926116652608,
            0.8080573790843986,
            0.7066104396485884,
            0.629197053548243,
            0.9130516187557053,
            0.6694728033909005,
            0.6401246088196706,
            0.7418744107713675
        ]
    },
    "pass_status": {
        "1": 0,
        "2": 0,
        "3": 0,
        "4": 0,
        "5": 1,
        "6": 0,
        "7": 0,
        "8": 0,
        "9": 0,
        "10": 1,
        "11": 1,
        "12": 0,
        "13": 1,
        "14": 1,
        "15": 1
    },
    "test_names": {
        "1": "Frequency Test",
        "2": "Block Frequency Test",
        "3": "Run Test",
        "4": "Longest Run of Ones Test",
        "5": "Binary Matrix Rank Test",
        "6": "Spectral Test",
        "7": "Non-overlapping Template Test",
        "8": "Overlapping Template Test",
        "9": "Universal Statistical Test",
        "10": "Linear Complexity Test",
        "11": "Serial Test",
        "12": "Approximate Entropy Test",
        "13": "Cumulative Sums Test",
        "14": "Random Excursions Test",
        "15": "Random Excursions Variant Test"
    },
    "pass_rate": 40.0
}