{
    "p_values": {
        "1": 5.718088070560357e-29,
        "2": 0.0,
        "3": 0.0,
        "4": 0.0003708008105544069,
        "5": 0.968582509118175,
        "6": 5.177480358829534e-07,
        "7": 9.247392154598024e-13,
        "8": 2.1938374025515802e-17,
        "9": 5.116603681603002e-64,
        "10": 0.9519754408036737,
        "12": 6.029843554534379e-82,
        "14": [
            0.4571448435418033,
            0.28403554071632875,
            0.15290556795308602,
            0.45281806435393757,
            0.857223076186539,
            0.7679960930206436,
            0.9858462128731907,
            0.33806704753211675
        ],
        "15": [
            0.5744390291714303,
            0.7231545670823016,
            0.8491049281482184,
            0.7173808884143212,
            0.6069054272179508,
            0.5816520703553031,
            0.6731485636901662,
            0.9605149582960633,
            0.6069054272179508,
            0.931665716594859,
            0.6920614909359382,
            0.7299934495999826,
            0.6735123594834926,
            0.47487019019606447,
            0.39355134840073724,
            0.2438789010901915,
            0.05137276959507452,
            0.011853757960921626
        ]
    },
    "pass_status": {
        "1": 0,
        "2": 0,
        "3": 0,
        "4": 0,
        "5": 1,
        "6": 0,
        "7": 0,
        "8": 0,
        "9": 0,
        "10": 1,
        "11": 1,
        "12": 0,
        "13": 1,
        "14": 1,
        "15": 1
    },
    "test_names": {
        "1": "Frequency Test",
        "2": "Block Frequency Test",
        "3": "Run Test",
        "4": "Longest Run of Ones Test",
        "5": "Binary Matrix Rank Test",
        "6": "Spectral Test",
        "7": "Non-overlapping Template Test",
        "8": "Overlapping Template Test",
        "9": "Universal Statistical Test",
        "10": "Linear Complexity Test",
        "11": "Serial Test",
        "12": "Approximate Entropy Test",
        "13": "Cumulative Sums Test",
        "14": "Random Excursions Test",
        "15": "Random Excursions Variant Test"
    },
    "pass_rate": 40.0
}