{
    "p_values": {
        "1": 3.725155171492084e-29,
        "2": 0.0,
        "3": 0.0,
        "4": 7.366889584564708e-05,
        "5": 0.8190913203774418,
        "6": 0.0033191592524302992,
        "7": 1.9430051827557393e-17,
        "8": 8.083040182659553e-14,
        "9": 6.3167154640962074e-58,
        "10": 0.4415991117244581,
        "12": 1.9120873465179099e-66,
        "14": [
            0.6174407198847317,
            0.9871452982736892,
            0.7172920881642906,
            0.12852651666592751,
            0.6161948290202651,
            0.5178029661339011,
            0.8735084993272993,
            0.0010068437591689572
        ],
        "15": [
            0.5125185930436823,
            0.5368820470525397,
            0.9317906798909645,
            0.9443637390474903,
            0.9180670209468027,
            0.5597506992586161,
            0.6788452994243183,
            0.6241487990076817,
            0.6434288435636205,
            0.4404006981390032,
            0.5929800980174267,
            0.6537616390703052,
            0.7483873375066029,
            0.9385028847784713,
            0.7801333481766646,
            0.9488156960255416,
            0.9048611294504482,
            0.7789555081438078
        ]
    },
    "pass_status": {
        "1": 0,
        "2": 0,
        "3": 0,
        "4": 0,
        "5": 1,
        "6": 0,
        "7": 0,
        "8": 0,
        "9": 0,
        "10": 1,
        "11": 1,
        "12": 0,
        "13": 1,
        "14": 0,
        "15": 1
    },
    "test_names": {
        "1": "Frequency Test",
        "2": "Block Frequency Test",
        "3": "Run Test",
        "4": "Longest Run of Ones Test",
        "5": "Binary Matrix Rank Test",
        "6": "Spectral Test",
        "7": "Non-overlapping Template Test",
        "8": "Overlapping Template Test",
        "9": "Universal Statistical Test",
        "10": "Linear Complexity Test",
        "11": "Serial Test",
        "12": "Approximate Entropy Test",
        "13": "Cumulative Sums Test",
        "14": "Random Excursions Test",
        "15": "Random Excursions Variant Test"
    },
    "pass_rate": 33.33333333333333
}