{
    "p_values": {
        "1": 1.647373852543516e-05,
        "2": 0.0,
        "3": 0.0,
        "4": 0.06602868213008467,
        "5": 0.9837137909420552,
        "6": 1.3071845366762971e-05,
        "7": 1.0872456666889486e-31,
        "8": 7.5050378426691975e-06,
        "9": 3.477249321917964e-59,
        "10": 0.21451091095564445,
        "12": 1.8517408616810336e-54,
        "14": [
            0.7370259695380069,
            0.28026845030091113,
            0.1645135911301061,
            0.30268384922447816,
            0.28481969678673996,
            0.7544145946649484,
            0.9458828769517275,
            0.4402835584763741
        ],
        "15": [
            0.6816158454598148,
            0.5958731520429619,
            0.6509851909308997,
            0.715634500655185,
            0.8246942345008477,
            0.4933375691119789,
            0.21394544151402217,
            0.3832219435738494,
            0.5063484017235746,
            0.6288843908969298,
            0.8342343224676747,
            0.6852883016375282,
            0.43754546239006853,
            0.5324571792664723,
            0.8411954188598705,
            0.8933688429876041,
            0.6067304843338805,
            0.6816158454598148
        ]
    },
    "pass_status": {
        "1": 0,
        "2": 0,
        "3": 0,
        "4": 1,
        "5": 1,
        "6": 0,
        "7": 0,
        "8": 0,
        "9": 0,
        "10": 1,
        "11": 1,
        "12": 0,
        "13": 1,
        "14": 1,
        "15": 1
    },
    "test_names": {
        "1": "Frequency Test",
        "2": "Block Frequency Test",
        "3": "Run Test",
        "4": "Longest Run of Ones Test",
        "5": "Binary Matrix Rank Test",
        "6": "Spectral Test",
        "7": "Non-overlapping Template Test",
        "8": "Overlapping Template Test",
        "9": "Universal Statistical Test",
        "10": "Linear Complexity Test",
        "11": "Serial Test",
        "12": "Approximate Entropy Test",
        "13": "Cumulative Sums Test",
        "14": "Random Excursions Test",
        "15": "Random Excursions Variant Test"
    },
    "pass_rate": 46.666666666666664
}