{
    "p_values": {
        "1": 0.2601655193244986,
        "2": 0.0,
        "3": 3.644696562387557e-27,
        "4": 0.00982593550208136,
        "5": 0.48036598731634655,
        "6": 2.631535393107013e-07,
        "7": 1.0434444223017574e-34,
        "8": 1.0905033196797343e-07,
        "9": 3.917814531856352e-42,
        "10": 0.9819940613037315,
        "12": 1.5649601096962998e-53,
        "14": [
            0.4474005759329771,
            0.1796508659530485,
            0.0004992613569756378,
            0.04416866907330554,
            0.4279024357236437,
            0.9695620016363571,
            0.2347830123292688,
            0.8157183265027839
        ],
        "15": [
            0.9359583058573716,
            0.8866325664554124,
            0.8302371985496455,
            0.6174656645159953,
            0.6855395542546914,
            0.966706609231974,
            0.9606113025453595,
            0.6553778845559657,
            0.9120671518304257,
            0.2244626820078678,
            0.4071894457353594,
            0.3740263849530854,
            0.8022508409186594,
            0.9120671518304257,
            0.8416540925967303,
            0.6459304930878033,
            0.689756037316511,
            0.8723285274941279
        ]
    },
    "pass_status": {
        "1": 1,
        "2": 0,
        "3": 0,
        "4": 0,
        "5": 1,
        "6": 0,
        "7": 0,
        "8": 0,
        "9": 0,
        "10": 1,
        "11": 1,
        "12": 0,
        "13": 1,
        "14": 0,
        "15": 1
    },
    "test_names": {
        "1": "Frequency Test",
        "2": "Block Frequency Test",
        "3": "Run Test",
        "4": "Longest Run of Ones Test",
        "5": "Binary Matrix Rank Test",
        "6": "Spectral Test",
        "7": "Non-overlapping Template Test",
        "8": "Overlapping Template Test",
        "9": "Universal Statistical Test",
        "10": "Linear Complexity Test",
        "11": "Serial Test",
        "12": "Approximate Entropy Test",
        "13": "Cumulative Sums Test",
        "14": "Random Excursions Test",
        "15": "Random Excursions Variant Test"
    },
    "pass_rate": 40.0
}