{
    "p_values": {
        "1": 1.21934473573327e-14,
        "2": 0.0,
        "3": 0.0,
        "4": 0.0713680635441903,
        "5": 0.9448411307109783,
        "6": 2.5303787707737774e-05,
        "7": 2.8955007967478024e-43,
        "8": 1.825939207064826e-10,
        "9": 9.846559198577079e-59,
        "10": 0.8741735339611187,
        "12": 1.9106332553077536e-63,
        "14": [
            0.005467558391618449,
            0.012007795050247135,
            0.838967457559531,
            0.6134196838023986,
            0.3589814580976379,
            0.8116875539988062,
            0.7473486501943986,
            0.7945691309591149
        ],
        "15": [
            0.7594197484155965,
            0.7444089125998363,
            0.7060690307859507,
            0.8375740044827231,
            0.6503566825900606,
            0.44074590289950477,
            0.7282173753524472,
            0.6137731164890038,
            0.5600471214005205,
            0.49656771600723437,
            0.34043167794644813,
            1.0,
            0.3984701873551295,
            0.4182822930851644,
            0.2917577896346548,
            0.33215096641960395,
            0.4079025786383784,
            0.27852952734052094
        ]
    },
    "pass_status": {
        "1": 0,
        "2": 0,
        "3": 0,
        "4": 1,
        "5": 1,
        "6": 0,
        "7": 0,
        "8": 0,
        "9": 0,
        "10": 1,
        "11": 1,
        "12": 0,
        "13": 1,
        "14": 0,
        "15": 1
    },
    "test_names": {
        "1": "Frequency Test",
        "2": "Block Frequency Test",
        "3": "Run Test",
        "4": "Longest Run of Ones Test",
        "5": "Binary Matrix Rank Test",
        "6": "Spectral Test",
        "7": "Non-overlapping Template Test",
        "8": "Overlapping Template Test",
        "9": "Universal Statistical Test",
        "10": "Linear Complexity Test",
        "11": "Serial Test",
        "12": "Approximate Entropy Test",
        "13": "Cumulative Sums Test",
        "14": "Random Excursions Test",
        "15": "Random Excursions Variant Test"
    },
    "pass_rate": 40.0
}