{
    "p_values": {
        "1": 2.8936358196226707e-38,
        "2": 0.0,
        "3": 0.0,
        "4": 0.0013388102635033105,
        "5": 0.5546179682459319,
        "6": 0.00019476505203433014,
        "7": 1.96801877298476e-74,
        "8": 1.2766852522677045e-20,
        "9": 5.1725446405993314e-76,
        "10": 0.7832969815703874,
        "12": 3.141524726363641e-110,
        "14": [
            0.5688769648251213,
            0.306991891906395,
            0.18895207020379193,
            0.09483391237662708,
            0.14247669037275063,
            0.05701752064144948,
            0.726349557530784,
            0.9849379396216594
        ],
        "15": [
            0.4504927601248232,
            0.4652088184521417,
            0.6378701798979456,
            0.7816565372093944,
            0.7592902583263772,
            0.5746280705895831,
            0.4866160457640506,
            0.22067136191984693,
            0.05623780387727592,
            0.9436280222029834,
            0.9349253116421173,
            0.8495154923650349,
            0.7082810122906027,
            0.46497646294543604,
            0.49508575626006945,
            1.0,
            0.7424326978058251,
            0.718737185219559
        ]
    },
    "pass_status": {
        "1": 0,
        "2": 0,
        "3": 0,
        "4": 0,
        "5": 1,
        "6": 0,
        "7": 0,
        "8": 0,
        "9": 0,
        "10": 1,
        "11": 1,
        "12": 0,
        "13": 1,
        "14": 1,
        "15": 1
    },
    "test_names": {
        "1": "Frequency Test",
        "2": "Block Frequency Test",
        "3": "Run Test",
        "4": "Longest Run of Ones Test",
        "5": "Binary Matrix Rank Test",
        "6": "Spectral Test",
        "7": "Non-overlapping Template Test",
        "8": "Overlapping Template Test",
        "9": "Universal Statistical Test",
        "10": "Linear Complexity Test",
        "11": "Serial Test",
        "12": "Approximate Entropy Test",
        "13": "Cumulative Sums Test",
        "14": "Random Excursions Test",
        "15": "Random Excursions Variant Test"
    },
    "pass_rate": 40.0
}