{
    "p_values": {
        "1": 2.628692578403167e-11,
        "2": 0.0,
        "3": 0.0,
        "4": 5.6554163643593875e-05,
        "5": 0.07761333039512136,
        "6": 7.567495657459857e-07,
        "7": 1.706035207802047e-22,
        "8": 1.4569678326848373e-16,
        "9": 2.6306852489423304e-71,
        "10": 0.9000084194697603,
        "12": 1.2211480705488393e-73,
        "14": [
            0.8328984111326785,
            0.6380143839464173,
            0.6105390349448393,
            0.7246366749552865,
            0.1414644819088054,
            0.58929066759883,
            0.19209767266042513,
            0.527552613729884
        ],
        "15": [
            0.716004795504331,
            0.7566836450106743,
            0.5790997419539188,
            0.5464935954065822,
            0.7138676734749972,
            0.6501474440948545,
            0.7542430423910373,
            0.6033317722918665,
            0.27133212189276534,
            0.23013934044341644,
            0.5253727863737021,
            0.6547208460185769,
            0.6231762238821175,
            0.7138676734749972,
            0.43308148126407064,
            0.4539504737647142,
            0.6055766163353464,
            0.3083693358615207
        ]
    },
    "pass_status": {
        "1": 0,
        "2": 0,
        "3": 0,
        "4": 0,
        "5": 1,
        "6": 0,
        "7": 0,
        "8": 0,
        "9": 0,
        "10": 1,
        "11": 1,
        "12": 0,
        "13": 1,
        "14": 1,
        "15": 1
    },
    "test_names": {
        "1": "Frequency Test",
        "2": "Block Frequency Test",
        "3": "Run Test",
        "4": "Longest Run of Ones Test",
        "5": "Binary Matrix Rank Test",
        "6": "Spectral Test",
        "7": "Non-overlapping Template Test",
        "8": "Overlapping Template Test",
        "9": "Universal Statistical Test",
        "10": "Linear Complexity Test",
        "11": "Serial Test",
        "12": "Approximate Entropy Test",
        "13": "Cumulative Sums Test",
        "14": "Random Excursions Test",
        "15": "Random Excursions Variant Test"
    },
    "pass_rate": 40.0
}