{
    "p_values": {
        "1": 0.9346467134571773,
        "2": 0.0,
        "3": 3.76671272699956e-23,
        "4": 0.0002477146991670878,
        "5": 0.7558247069292964,
        "6": 1.9993103466030376e-06,
        "7": 2.83351027994817e-21,
        "8": 3.426100725756382e-11,
        "9": 4.974411807396722e-47,
        "10": 0.8407884965248213,
        "12": 2.1079927303105356e-55,
        "14": [
            0.4167260223488306,
            0.33379556873768823,
            0.7990273059464005,
            0.9858156041599069,
            0.1996292414781185,
            0.45954754986400026,
            0.2618444699211605,
            0.29309576564667156
        ],
        "15": [
            0.8669953072757568,
            0.8584935682843173,
            0.5873846060161538,
            0.8486428708842394,
            0.8780438721426684,
            0.4662431463344908,
            0.5712894276142568,
            0.8161035391800904,
            0.9083761104061354,
            0.6452662590001792,
            0.4853784213496358,
            0.6340147941325729,
            1.0,
            0.8780438721426684,
            0.7746671475044713,
            0.8731985050379366,
            0.9526090563278722,
            0.8070478564508796
        ]
    },
    "pass_status": {
        "1": 1,
        "2": 0,
        "3": 0,
        "4": 0,
        "5": 1,
        "6": 0,
        "7": 0,
        "8": 0,
        "9": 0,
        "10": 1,
        "11": 1,
        "12": 0,
        "13": 1,
        "14": 1,
        "15": 1
    },
    "test_names": {
        "1": "Frequency Test",
        "2": "Block Frequency Test",
        "3": "Run Test",
        "4": "Longest Run of Ones Test",
        "5": "Binary Matrix Rank Test",
        "6": "Spectral Test",
        "7": "Non-overlapping Template Test",
        "8": "Overlapping Template Test",
        "9": "Universal Statistical Test",
        "10": "Linear Complexity Test",
        "11": "Serial Test",
        "12": "Approximate Entropy Test",
        "13": "Cumulative Sums Test",
        "14": "Random Excursions Test",
        "15": "Random Excursions Variant Test"
    },
    "pass_rate": 46.666666666666664
}