{
    "p_values": {
        "1": 6.852309155531427e-21,
        "2": 0.0,
        "3": 0.0,
        "4": 5.2881778552518234e-08,
        "5": 0.02372522794912339,
        "6": 0.0004557977334068082,
        "7": 1.9539831667798645e-06,
        "8": 7.838557014547993e-10,
        "9": 4.2641470727035016e-47,
        "10": 0.3565151546365126,
        "12": 5.623225022729729e-47,
        "14": [
            0.6336926058956974,
            0.6500247640242284,
            0.45136225115947937,
            0.015042145722429612,
            0.47382490760572016,
            0.9167312722904077,
            0.5417769791532641,
            0.8729705199911671
        ],
        "15": [
            1.0,
            0.8905403762382125,
            0.7007167881475308,
            0.6527269942040037,
            0.8869743120400594,
            0.6004281385485983,
            0.8115975090747047,
            0.950924583799356,
            0.5224312849615645,
            0.6698153575994166,
            0.9020346492544503,
            0.6335534753768335,
            0.9678610107623294,
            0.49958961640701727,
            0.3190666458464234,
            0.5346798868923823,
            0.8905403762382125,
            0.9587607499379828
        ]
    },
    "pass_status": {
        "1": 0,
        "2": 0,
        "3": 0,
        "4": 0,
        "5": 1,
        "6": 0,
        "7": 0,
        "8": 0,
        "9": 0,
        "10": 1,
        "11": 1,
        "12": 0,
        "13": 1,
        "14": 1,
        "15": 1
    },
    "test_names": {
        "1": "Frequency Test",
        "2": "Block Frequency Test",
        "3": "Run Test",
        "4": "Longest Run of Ones Test",
        "5": "Binary Matrix Rank Test",
        "6": "Spectral Test",
        "7": "Non-overlapping Template Test",
        "8": "Overlapping Template Test",
        "9": "Universal Statistical Test",
        "10": "Linear Complexity Test",
        "11": "Serial Test",
        "12": "Approximate Entropy Test",
        "13": "Cumulative Sums Test",
        "14": "Random Excursions Test",
        "15": "Random Excursions Variant Test"
    },
    "pass_rate": 40.0
}