{
    "p_values": {
        "1": 0.009214275678843776,
        "2": 0.0,
        "3": 6.330979892532516e-26,
        "4": 0.009970748128765871,
        "5": 0.6680125482614389,
        "6": 0.0008369001811729186,
        "7": 4.705527927796906e-18,
        "8": 2.007862990682593e-12,
        "9": 3.092702646830878e-56,
        "10": 0.2370976126994763,
        "12": 1.4180646577516088e-69,
        "14": [
            0.9518724858381543,
            0.34136552823811345,
            0.8976619826445705,
            0.9625657732472964,
            0.9910411208071005,
            0.8911692849968064,
            0.7344332730966945,
            0.9372190890497989
        ],
        "15": [
            0.4782840785166479,
            0.483746567941143,
            0.4578072968725576,
            0.5954089339529973,
            0.8326212028332123,
            0.7798014062420897,
            0.9623081747334636,
            0.404400384992468,
            0.4178594602922172,
            0.5972547233699116,
            0.46410347443092703,
            0.6821264677268124,
            0.7696054100071619,
            0.7246620479349835,
            0.9491918218684315,
            0.9299377450166265,
            0.8556664156057064,
            0.8509197925468707
        ]
    },
    "pass_status": {
        "1": 0,
        "2": 0,
        "3": 0,
        "4": 0,
        "5": 1,
        "6": 0,
        "7": 0,
        "8": 0,
        "9": 0,
        "10": 1,
        "11": 1,
        "12": 0,
        "13": 1,
        "14": 1,
        "15": 1
    },
    "test_names": {
        "1": "Frequency Test",
        "2": "Block Frequency Test",
        "3": "Run Test",
        "4": "Longest Run of Ones Test",
        "5": "Binary Matrix Rank Test",
        "6": "Spectral Test",
        "7": "Non-overlapping Template Test",
        "8": "Overlapping Template Test",
        "9": "Universal Statistical Test",
        "10": "Linear Complexity Test",
        "11": "Serial Test",
        "12": "Approximate Entropy Test",
        "13": "Cumulative Sums Test",
        "14": "Random Excursions Test",
        "15": "Random Excursions Variant Test"
    },
    "pass_rate": 40.0
}