{
    "p_values": {
        "1": 1.5798125233452853e-09,
        "2": 0.0,
        "3": 0.0,
        "4": 0.00019139343694374577,
        "5": 0.2232549542515111,
        "6": 1.6888879722480996e-07,
        "7": 1.0163011449781338e-66,
        "8": 2.2806967004418087e-19,
        "9": 2.7304039876791143e-85,
        "10": 0.0531319747618725,
        "12": 2.1578232261097128e-94,
        "14": [
            0.973246337232544,
            0.287241683425561,
            0.8935834522072044,
            0.17558838731303836,
            0.22064030793671058,
            0.49292592375135647,
            0.023006794405556703,
            9.930244022034029e-09
        ],
        "15": [
            0.6055766163353464,
            0.8676323347781927,
            0.5637028616507731,
            0.3864762307712327,
            0.7388826803635272,
            0.897278961260083,
            0.8272593465627114,
            0.9233418401809065,
            0.9306406489398111,
            0.9361862934730594,
            0.5509849875850936,
            0.3627265064850981
        ]
    },
    "pass_status": {
        "1": 0,
        "2": 0,
        "3": 0,
        "4": 0,
        "5": 1,
        "6": 0,
        "7": 0,
        "8": 0,
        "9": 0,
        "10": 1,
        "11": 1,
        "12": 0,
        "13": 1,
        "14": 0,
        "15": 1
    },
    "test_names": {
        "1": "Frequency Test",
        "2": "Block Frequency Test",
        "3": "Run Test",
        "4": "Longest Run of Ones Test",
        "5": "Binary Matrix Rank Test",
        "6": "Spectral Test",
        "7": "Non-overlapping Template Test",
        "8": "Overlapping Template Test",
        "9": "Universal Statistical Test",
        "10": "Linear Complexity Test",
        "11": "Serial Test",
        "12": "Approximate Entropy Test",
        "13": "Cumulative Sums Test",
        "14": "Random Excursions Test",
        "15": "Random Excursions Variant Test"
    },
    "pass_rate": 33.33333333333333
}