{
    "p_values": {
        "1": 5.264681174617984e-25,
        "2": 0.0,
        "3": 0.0,
        "4": 0.21391594890300344,
        "5": 0.07478007410772558,
        "6": 4.43433219590859e-05,
        "7": 4.007349213772876e-38,
        "8": 2.575750144341115e-07,
        "9": 5.676553583997723e-52,
        "10": 0.816152164719517,
        "12": 1.9108631122193094e-54,
        "14": [
            0.3687420534236656,
            0.0773253722530673,
            0.8074377918275382,
            0.7502330221116583,
            0.30064562341929574,
            0.579871145226518,
            0.7491192002650141,
            0.19647803689922586
        ],
        "15": [
            0.8400716444402775,
            0.8438810721922346,
            1.0,
            0.8836511338597889,
            0.5790997419539189,
            0.31931302422735064,
            0.3364168335882751,
            0.316923044733213,
            0.23850255227232542,
            0.26725749315438785,
            0.0655521611655026,
            0.04384554166017639,
            0.13522636100691607,
            0.18770023708766914,
            0.2863293722390635,
            0.39746692542259277,
            0.2990994282938151,
            0.3818598292804778
        ]
    },
    "pass_status": {
        "1": 0,
        "2": 0,
        "3": 0,
        "4": 1,
        "5": 1,
        "6": 0,
        "7": 0,
        "8": 0,
        "9": 0,
        "10": 1,
        "11": 1,
        "12": 0,
        "13": 1,
        "14": 1,
        "15": 1
    },
    "test_names": {
        "1": "Frequency Test",
        "2": "Block Frequency Test",
        "3": "Run Test",
        "4": "Longest Run of Ones Test",
        "5": "Binary Matrix Rank Test",
        "6": "Spectral Test",
        "7": "Non-overlapping Template Test",
        "8": "Overlapping Template Test",
        "9": "Universal Statistical Test",
        "10": "Linear Complexity Test",
        "11": "Serial Test",
        "12": "Approximate Entropy Test",
        "13": "Cumulative Sums Test",
        "14": "Random Excursions Test",
        "15": "Random Excursions Variant Test"
    },
    "pass_rate": 46.666666666666664
}